cmweather/__init__.py
cmweather/_cm.py
cmweather/_cm_colorblind.py
cmweather/balance-rgb.txt
cmweather/chase-spectral-rgb.txt
cmweather/cm.py
cmweather/cm_colorblind.py
cmweather/crameri-michelson-oleron-depol.txt
cmweather/crameri-michelson-roma-rhohv.txt
cmweather/plasmidis-rgb.txt
cmweather/spectral-extended-rgb.txt
cmweather-0.3.1.dist-info/LICENSE
cmweather-0.3.1.dist-info/METADATA
cmweather-0.3.1.dist-info/WHEEL
cmweather-0.3.1.dist-info/top_level.txt
cmweather-0.3.1.dist-info/RECORD
