Metadata-Version: 2.1
Name: cmweather
Version: 0.3.1
Summary: A library of useful colormaps when visualizing weather and climate data, with numerous color vision deficiency friendly options
Home-page: https://github.com/openradar/cmweather
Maintainer: Open Radar Community
Maintainer-email: mgrover@anl.gov
License: MIT license
Project-URL: Documentation, https://github.com/openradar/cmweather
Project-URL: Source, https://github.com/openradar/cmweather
Project-URL: Tracker, https://github.com/openradar/cmweather/issues
Keywords: cmweather
Classifier: Development Status :: 2 - Pre-Alpha
Classifier: License :: OSI Approved :: MIT License
Classifier: Natural Language :: English
Classifier: Programming Language :: Python :: 3
Classifier: Programming Language :: Python :: 3.6
Classifier: Programming Language :: Python :: 3.7
Classifier: Programming Language :: Python :: 3.8
Classifier: Topic :: Scientific/Engineering
Classifier: Operating System :: OS Independent
Classifier: Intended Audience :: Science/Research
Requires-Python: >=3.6
License-File: LICENSE
Requires-Dist: numpy
Requires-Dist: matplotlib
